
[{
        "addTime": "2019-05-31 15:30:53",
        "iconName": "白雪皇后",
        "iconUrl": "https://vthumb.ykimg.com/054101015E68950E5A50FC94C4B63CDD",
        "isDeleted": 0,
        "modifyTime": "2020-11-15 14:45:09",
        "number": 2,
        "playUrl": "http://poerty.wuqiongda8888.com/chinestonghua/1.mp4",
        "remark": "",
        "rid": 2779,
        "sourceId": 57
    }, {
        "addTime": "2019-05-31 15:30:53",
        "iconName": "卖火柴的小女孩",
        "iconUrl": "https://vthumb.ykimg.com/054101015E68950E5A50FC94C4B63CDD",
        "isDeleted": 0,
        "modifyTime": "2020-11-15 14:45:09",
        "number": 3,
        "playUrl": "http://poerty.wuqiongda8888.com/chinestonghua/2.mp4",
        "remark": "",
        "rid": 2780,
        "sourceId": 57
    }, {
        "addTime": "2019-05-31 15:30:53",
        "iconName": "小意达的花",
        "iconUrl": "https://vthumb.ykimg.com/054101015E68950E5A50FC94C4B63CDD",
        "isDeleted": 0,
        "modifyTime": "2020-11-15 14:45:09",
        "number": 4,
        "playUrl": "http://poerty.wuqiongda8888.com/chinestonghua/3.mp4",
        "remark": "",
        "rid": 2781,
        "sourceId": 57
    }, {
        "addTime": "2019-05-31 15:30:53",
        "iconName": "顽皮的孩子",
        "iconUrl": "https://vthumb.ykimg.com/054101015E68950E5A50FC94C4B63CDD",
        "isDeleted": 0,
        "modifyTime": "2020-11-15 14:45:09",
        "number": 5,
        "playUrl": "http://poerty.wuqiongda8888.com/chinestonghua/4.mp4",
        "remark": "",
        "rid": 2782,
        "sourceId": 57
    }, {
        "addTime": "2019-05-31 15:30:53",
        "iconName": "雏菊",
        "iconUrl": "https://vthumb.ykimg.com/054101015E68950E5A50FC94C4B63CDD",
        "isDeleted": 0,
        "modifyTime": "2020-11-15 14:45:09",
        "number": 6,
        "playUrl": "http://poerty.wuqiongda8888.com/chinestonghua/5.mp4",
        "remark": "",
        "rid": 2783,
        "sourceId": 57
    }, {
        "addTime": "2019-05-31 15:30:53",
        "iconName": "笨蛋汉斯",
        "iconUrl": "https://vthumb.ykimg.com/054101015E68950E5A50FC94C4B63CDD",
        "isDeleted": 0,
        "modifyTime": "2020-11-15 14:45:09",
        "number": 7,
        "playUrl": "http://poerty.wuqiongda8888.com/chinestonghua/6.mp4",
        "remark": "",
        "rid": 2784,
        "sourceId": 57
    }, {
        "addTime": "2019-05-31 15:30:53",
        "iconName": "坚定的锡兵",
        "iconUrl": "https://vthumb.ykimg.com/054101015E68950E5A50FC94C4B63CDD",
        "isDeleted": 0,
        "modifyTime": "2020-11-15 14:45:09",
        "number": 8,
        "playUrl": "http://poerty.wuqiongda8888.com/chinestonghua/7.mp4",
        "remark": "",
        "rid": 2785,
        "sourceId": 57
    }, {
        "addTime": "2019-05-31 15:30:53",
        "iconName": "牧羊女",
        "iconUrl": "https://vthumb.ykimg.com/054101015E68950E5A50FC94C4B63CDD",
        "isDeleted": 0,
        "modifyTime": "2020-11-15 14:45:09",
        "number": 9,
        "playUrl": "http://poerty.wuqiongda8888.com/chinestonghua/8.mp4",
        "remark": "",
        "rid": 2786,
        "sourceId": 57
    }, {
        "addTime": "2019-05-31 15:30:53",
        "iconName": "拇指姑娘",
        "iconUrl": "https://vthumb.ykimg.com/054101015E68950E5A50FC94C4B63CDD",
        "isDeleted": 0,
        "modifyTime": "2020-11-15 14:45:09",
        "number": 10,
        "playUrl": "http://poerty.wuqiongda8888.com/chinestonghua/9.mp4",
        "remark": "",
        "rid": 2787,
        "sourceId": 57
    }, {
        "addTime": "2019-05-31 15:30:53",
        "iconName": "最后的珠子",
        "iconUrl": "https://vthumb.ykimg.com/054101015E68950E5A50FC94C4B63CDD",
        "isDeleted": 0,
        "modifyTime": "2020-11-15 14:45:09",
        "number": 11,
        "playUrl": "http://poerty.wuqiongda8888.com/chinestonghua/10.mp4",
        "remark": "",
        "rid": 2788,
        "sourceId": 57
    }, {
        "addTime": "2019-05-31 15:30:53",
        "iconName": "大克劳斯和小克劳斯",
        "iconUrl": "https://vthumb.ykimg.com/054101015E68950E5A50FC94C4B63CDD",
        "isDeleted": 0,
        "modifyTime": "2020-11-15 14:45:09",
        "number": 12,
        "playUrl": "http://poerty.wuqiongda8888.com/chinestonghua/11.mp4",
        "remark": "",
        "rid": 2789,
        "sourceId": 57
    }, {
        "addTime": "2019-05-31 15:30:53",
        "iconName": "踩面包的小女孩",
        "iconUrl": "https://vthumb.ykimg.com/054101015E68950E5A50FC94C4B63CDD",
        "isDeleted": 0,
        "modifyTime": "2020-11-15 14:45:09",
        "number": 13,
        "playUrl": "http://poerty.wuqiongda8888.com/chinestonghua/12.mp4",
        "remark": "",
        "rid": 2790,
        "sourceId": 57
    }, {
        "addTime": "2019-05-31 15:30:53",
        "iconName": "打火匣",
        "iconUrl": "https://vthumb.ykimg.com/054101015E68950E5A50FC94C4B63CDD",
        "isDeleted": 0,
        "modifyTime": "2020-11-15 14:45:09",
        "number": 14,
        "playUrl": "http://poerty.wuqiongda8888.com/chinestonghua/13.mp4",
        "remark": "",
        "rid": 2791,
        "sourceId": 57
    }, {
        "addTime": "2019-05-31 15:30:53",
        "iconName": "飞箱",
        "iconUrl": "https://vthumb.ykimg.com/054101015E68950E5A50FC94C4B63CDD",
        "isDeleted": 0,
        "modifyTime": "2020-11-15 14:45:09",
        "number": 15,
        "playUrl": "http://poerty.wuqiongda8888.com/chinestonghua/14.mp4",
        "remark": "",
        "rid": 2792,
        "sourceId": 57
    }, {
        "addTime": "2019-05-31 15:30:53",
        "iconName": "夜莺",
        "iconUrl": "https://vthumb.ykimg.com/054101015E68950E5A50FC94C4B63CDD",
        "isDeleted": 0,
        "modifyTime": "2020-11-15 14:45:09",
        "number": 16,
        "playUrl": "http://poerty.wuqiongda8888.com/chinestonghua/15.mp4",
        "remark": "",
        "rid": 2793,
        "sourceId": 57
    }, {
        "addTime": "2019-05-31 15:30:53",
        "iconName": "三个小矮人",
        "iconUrl": "https://vthumb.ykimg.com/054101015E68950E5A50FC94C4B63CDD",
        "isDeleted": 0,
        "modifyTime": "2020-11-15 14:45:10",
        "number": 17,
        "playUrl": "http://poerty.wuqiongda8888.com/chinestonghua/16.mp4",
        "remark": "",
        "rid": 2794,
        "sourceId": 57
    }, {
        "addTime": "2019-05-31 15:30:53",
        "iconName": "海的女儿",
        "iconUrl": "https://vthumb.ykimg.com/054101015E68950E5A50FC94C4B63CDD",
        "isDeleted": 0,
        "modifyTime": "2020-11-15 14:45:10",
        "number": 18,
        "playUrl": "http://poerty.wuqiongda8888.com/chinestonghua/17.mp4",
        "remark": "",
        "rid": 2795,
        "sourceId": 57
    }, {
        "addTime": "2019-05-31 15:30:53",
        "iconName": "野天鹅",
        "iconUrl": "https://vthumb.ykimg.com/054101015E68950E5A50FC94C4B63CDD",
        "isDeleted": 0,
        "modifyTime": "2020-11-15 14:45:10",
        "number": 19,
        "playUrl": "http://poerty.wuqiongda8888.com/chinestonghua/18.mp4",
        "remark": "",
        "rid": 2796,
        "sourceId": 57
    }, {
        "addTime": "2019-05-31 15:30:53",
        "iconName": "梦神",
        "iconUrl": "https://vthumb.ykimg.com/054101015E68950E5A50FC94C4B63CDD",
        "isDeleted": 0,
        "modifyTime": "2020-11-15 14:45:10",
        "number": 20,
        "playUrl": "http://poerty.wuqiongda8888.com/chinestonghua/19.mp4",
        "remark": "",
        "rid": 2797,
        "sourceId": 57
    }, {
        "addTime": "2019-05-31 15:30:53",
        "iconName": "聪明的小裁缝",
        "iconUrl": "https://vthumb.ykimg.com/054101015E68950E5A50FC94C4B63CDD",
        "isDeleted": 0,
        "modifyTime": "2020-11-15 14:45:10",
        "number": 21,
        "playUrl": "http://poerty.wuqiongda8888.com/chinestonghua/20.mp4",
        "remark": "",
        "rid": 2798,
        "sourceId": 57
    }]
